GPErks/__init__.py
GPErks/constants.py
GPErks/gp/__init__.py
GPErks/gp/experiment.py
GPErks/gp/mean.py
GPErks/gp/model.py
GPErks/gp/data/__init__.py
GPErks/gp/data/data_scaler.py
GPErks/gp/data/dataset.py
GPErks/gp/data/scaled_data.py
GPErks/log/__init__.py
GPErks/log/logger.py
GPErks/perks/__init__.py
GPErks/perks/cross_validation.py
GPErks/perks/diagnostics.py
GPErks/perks/gsa.py
GPErks/perks/inference.py
GPErks/plot/__init__.py
GPErks/plot/gsa.py
GPErks/plot/options.py
GPErks/plot/plottable.py
GPErks/serialization/__init__.py
GPErks/serialization/config.py
GPErks/serialization/labels.py
GPErks/serialization/path.py
GPErks/serialization/runtime.py
GPErks/train/__init__.py
GPErks/train/early_stop.py
GPErks/train/emulator.py
GPErks/train/snapshot.py
GPErks/train/train_stats.py
GPErks/train/trainable.py
GPErks/utils/__init__.py
GPErks/utils/array.py
GPErks/utils/concurrency.py
GPErks/utils/indices.py
GPErks/utils/metrics.py
GPErks/utils/plotting.py
GPErks/utils/random.py
GPErks/utils/test_functions.py
GPErks/utils/test_functions_gsa.py
GPErks/utils/time.py
GPErks-0.1.0.dist-info/LICENSE
GPErks-0.1.0.dist-info/METADATA
GPErks-0.1.0.dist-info/WHEEL
GPErks-0.1.0.dist-info/top_level.txt
GPErks-0.1.0.dist-info/RECORD
